Workbook

Sheet Summary
A1: BSA v3 — What still needs improvement (for approval)
A2: Development prototype → clean, functioning handover to Grid's development team. Review the Backlog, set Approval per row, then we proceed in batches.
A4: Backlog by area and priority
A5: Area | B5: P1 | C5: P2 | D5: P3 | E5: Total | F5: Approved
A6: Regional expansion | B6: =COUNTIFS('Improvement Backlog'!$B$5:$B$40,$A6,'Improvement Backlog'!$H$5:$H$40,"P1") -> 4 | C6: =COUNTIFS('Improvement Backlog'!$B$5:$B$40,$A6,'Improvement Backlog'!$H$5:$H$40,"P2") -> 4 | D6: =COUNTIFS('Improvement Backlog'!$B$5:$B$40,$A6,'Improvement Backlog'!$H$5:$H$40,"P3") -> 0 | E6: =SUM(B6:D6) -> 8 | F6: =COUNTIFS('Improvement Backlog'!$B$5:$B$40,$A6,'Improvement Backlog'!$L$5:$L$40,"Approve") -> 0
A7: Data & scoring | B7: =COUNTIFS('Improvement Backlog'!$B$5:$B$40,$A7,'Improvement Backlog'!$H$5:$H$40,"P1") -> 0 | C7: =COUNTIFS('Improvement Backlog'!$B$5:$B$40,$A7,'Improvement Backlog'!$H$5:$H$40,"P2") -> 4 | D7: =COUNTIFS('Improvement Backlog'!$B$5:$B$40,$A7,'Improvement Backlog'!$H$5:$H$40,"P3") -> 3 | E7: =SUM(B7:D7) -> 7 | F7: =COUNTIFS('Improvement Backlog'!$B$5:$B$40,$A7,'Improvement Backlog'!$L$5:$L$40,"Approve") -> 0
A8: AI layer | B8: =COUNTIFS('Improvement Backlog'!$B$5:$B$40,$A8,'Improvement Backlog'!$H$5:$H$40,"P1") -> 2 | C8: =COUNTIFS('Improvement Backlog'!$B$5:$B$40,$A8,'Improvement Backlog'!$H$5:$H$40,"P2") -> 1 | D8: =COUNTIFS('Improvement Backlog'!$B$5:$B$40,$A8,'Improvement Backlog'!$H$5:$H$40,"P3") -> 1 | E8: =SUM(B8:D8) -> 4 | F8: =COUNTIFS('Improvement Backlog'!$B$5:$B$40,$A8,'Improvement Backlog'!$L$5:$L$40,"Approve") -> 0
A9: Architecture | B9: =COUNTIFS('Improvement Backlog'!$B$5:$B$40,$A9,'Improvement Backlog'!$H$5:$H$40,"P1") -> 0 | C9: =COUNTIFS('Improvement Backlog'!$B$5:$B$40,$A9,'Improvement Backlog'!$H$5:$H$40,"P2") -> 4 | D9: =COUNTIFS('Improvement Backlog'!$B$5:$B$40,$A9,'Improvement Backlog'!$H$5:$H$40,"P3") -> 1 | E9: =SUM(B9:D9) -> 5 | F9: =COUNTIFS('Improvement Backlog'!$B$5:$B$40,$A9,'Improvement Backlog'!$L$5:$L$40,"Approve") -> 0
A10: Operations | B10: =COUNTIFS('Improvement Backlog'!$B$5:$B$40,$A10,'Improvement Backlog'!$H$5:$H$40,"P1") -> 3 | C10: =COUNTIFS('Improvement Backlog'!$B$5:$B$40,$A10,'Improvement Backlog'!$H$5:$H$40,"P2") -> 1 | D10: =COUNTIFS('Improvement Backlog'!$B$5:$B$40,$A10,'Improvement Backlog'!$H$5:$H$40,"P3") -> 0 | E10: =SUM(B10:D10) -> 4 | F10: =COUNTIFS('Improvement Backlog'!$B$5:$B$40,$A10,'Improvement Backlog'!$L$5:$L$40,"Approve") -> 0
A11: Security | B11: =COUNTIFS('Improvement Backlog'!$B$5:$B$40,$A11,'Improvement Backlog'!$H$5:$H$40,"P1") -> 1 | C11: =COUNTIFS('Improvement Backlog'!$B$5:$B$40,$A11,'Improvement Backlog'!$H$5:$H$40,"P2") -> 2 | D11: =COUNTIFS('Improvement Backlog'!$B$5:$B$40,$A11,'Improvement Backlog'!$H$5:$H$40,"P3") -> 1 | E11: =SUM(B11:D11) -> 4 | F11: =COUNTIFS('Improvement Backlog'!$B$5:$B$40,$A11,'Improvement Backlog'!$L$5:$L$40,"Approve") -> 0
A12: User experience | B12: =COUNTIFS('Improvement Backlog'!$B$5:$B$40,$A12,'Improvement Backlog'!$H$5:$H$40,"P1") -> 1 | C12: =COUNTIFS('Improvement Backlog'!$B$5:$B$40,$A12,'Improvement Backlog'!$H$5:$H$40,"P2") -> 3 | D12: =COUNTIFS('Improvement Backlog'!$B$5:$B$40,$A12,'Improvement Backlog'!$H$5:$H$40,"P3") -> 0 | E12: =SUM(B12:D12) -> 4 | F12: =COUNTIFS('Improvement Backlog'!$B$5:$B$40,$A12,'Improvement Backlog'!$L$5:$L$40,"Approve") -> 0
A13: Total | B13: =SUM(B6:B12) -> 11 | C13: =SUM(C6:C12) -> 19 | D13: =SUM(D6:D12) -> 6 | E13: =SUM(E6:E12) -> 36 | F13: =SUM(F6:F12) -> 0
A15: How to read the workbook
A16: • Improvement Backlog — every open item: what needs improving, current state, how to improve, the implementation needed and the desired outcome. Yellow 'Approval' column is yours to fill (Approve / Defer / Reject / Discuss).
A17: • Cavite-Batangas Data Plan — 12 steps to source Cavite and Batangas data (Overpass API + PSA, BIR, broker and DPWH sources) and load it into Neon with its Truth Layer.
A18: • Overpass Query Templates — ready-to-test Overpass QL for provinces, tiles, brands, malls, transport and barangay boundaries.
A19: • Data Coverage Matrix — what data exists today for NCR, Davao, Cavite and Batangas, and where the gaps get filled from.
A20: • Sources — references used for the Overpass guidance, admin levels, census figures and BIR RDOs.
A21: • Suggested first batch (P1): R-01, R-02, R-03, R-04, I-01, I-02, O-01, O-02, O-03, S-01, U-01.

Sheet Improvement Backlog
A1: BSA v3 — Improvement Backlog (development prototype → clean handover)
A2: Status as of 23 Sep 2026, after fix batches 1–5. Set 'Approval' per row (Approve / Defer / Reject / Discuss). Priority: P1 = before handover · P2 = early dev-team sprint · P3 = later. Effort: S ≤1 day · M 2–5 days · L 1–3 weeks.
A4: ID | B4: Area | C4: What still needs improvement | D4: Current state / why it matters | E4: How to improve | F4: Implementation needed | G4: Desired outcome | H4: Priority | I4: Effort | J4: Owner (skill) | K4: Depends on | L4: Approval | M4: Reviewer notes
A5: R-01 | B5: Regional expansion | C5: Region support is hard-coded to NCR (and part of Davao) | D5: ingestOsm.ts sweeps one fixed NCR_BBOX; the warm grid (NCR_CENTERS), corridor resolver (inferCorridor), zonal city matcher (canonicalNcrCity) and populate.ts regions are NCR/Davao only. A Cavite or Batangas site gets proxy lease comps (Quezon City; Bacoor → Las Piñas), no zonal cross-check, no mall or traffic context, and no demographics. | E5: Introduce a single region registry and make every ingest script and resolver region-aware, so adding a province is configuration + data, not code changes. | F5: New lib/geo/regions.ts: { key, name, psgcProvinceCodes, bbox, overpassArea, warmCentres, corridors }. Add --region=<key> to ingestOsm.ts, populate.ts and the zonal ETL. Replace canonicalNcrCity/inferCorridor with canonicalCity(region)/inferCorridor(region). Add region + province to candidate_site (derived from the pinned point). | G5: Any supported province can be switched on by adding a registry entry and loading its data. Cavite and Batangas sites are analysed on local data instead of NCR proxies. | H5: P1 | I5: M | J5: 02 Database · 01 Senior Web
A6: R-02 | B6: Regional expansion | C6: No real administrative boundaries (barangay / city polygons) | D6: demographic_cell.geom is a 600 m circle around a centroid, not the barangay shape. POIs are stored with city/barangay = NULL, so nothing can be filtered or reported by LGU. | E6: Load official PSGC boundary polygons (region → province → city/municipality → barangay) and tag every POI and site with its PSGC codes by point-in-polygon. | F6: New table admin_boundary (psgc_code PK, level, name, parent_psgc, geom MultiPolygon, GiST index, truth_layer Verified). Loader prisma/loadBoundaries.ts reading the PSGC shapefiles (altcoder/philippines-psgc-shapefiles, MIT, PSGC Q4-2023). SQL backfill: UPDATE poi SET city/barangay/psgc FROM admin_boundary WHERE ST_Contains. Same for candidate_site and mall_property. | G6: Every point knows its barangay, city and province. Reports, White-Space areas and zonal lookups use true LGU boundaries. | H6: P1 | I6: M | J6: 02 Database
A7: R-03 | B7: Regional expansion | C7: OSM/Overpass sweep truncates results in dense areas | D7: Each vertical is fetched with ONE bbox query for all of NCR and 'out center 600' (brands: 200). Dense categories (food, convenience, pharmacy) hit the cap, so coverage is silently incomplete. Scaling that to a whole province is worse. | E7: Tile each region into ~0.05°–0.1° cells and query per tile + vertical, sequentially with pauses; if a tile returns the cap, split it into four and retry. | F7: osmService.establishmentsInTiles(region, vertical): adaptive quad-tiling, 2.5 s pause, endpoint rotation (already present), resumable checkpoint (poi_coverage rows with source='bulk'). Log per-tile counts. Keep total ≤ ~10,000 queries/day per Overpass guidance. | G7: Complete, non-truncated establishment coverage per province, reproducible and resumable. | H7: P1 | I7: M | J7: 02 Database · 06 Research | K7: R-01
A8: R-04 | B8: Regional expansion | C8: Demographics exist only for NCR (283 barangays) + 13 Davao cells | D8: Site Fit demand, Daypart and White-Space need population. Outside NCR, Site Fit can't score, so the composite is capped at CAUTION and confidence reads Low. | E8: Load PSA 2020 Census barangay populations for Cavite and Batangas onto the real barangay polygons; keep estimated bands (income, daytime) clearly Assumed. | F8: Source: PSA 2020 CPH barangay tables (Region IV-A). ETL → prisma/data/demographics.<region>.json (psgc_code, barangay, city, population [Verified], income_band/daytime_pop [Assumed]) → loadDemographics with geom from admin_boundary. OSM barangay nodes' population tag is a cross-check only. | G8: Cavite (4,344,829 people, 2020) and Batangas (2,908,494) sites get real demand scores and White-Space areas, with honest Truth Layers. | H8: P1 | I8: M | J8: 02 Database · 06 Research | K8: R-02
A9: R-05 | B9: Regional expansion | C9: BIR zonal values cover NCR only | D9: Lease zonal cross-check and the Land zoning screen return 'unknown' outside NCR. | E9: Run the existing NCR zonal ETL on the BIR schedules for the Cavite and Batangas RDOs and load with region = 'IV-A'. | F9: Collect latest BIR zonal workbooks: RDO 54A (Trece Martires, East Cavite), RDO 54B (Bacoor, West Cavite), RDO 58 and 59 (Batangas). Reuse the NCR ETL (label canonicalisation, ₱ parsing, barangay + city grain). Extend canonicalCity for provincial LGUs. Load via loadZonal (idempotent natural key). | G9: Zonal band, rent-to-zonal cross-check and zoning screen work for Cavite and Batangas — still framed as tax-reference floors only. | H9: P2 | I9: M | J9: 02 Database · 07 Broker | K9: R-01
A10: R-06 | B10: Regional expansion | C10: No lease comparables outside NCR/Davao corridors | D10: Lease Benchmark falls back to a Quezon City proxy (flagged Projected) for every Cavite/Batangas site. | E10: Define provincial corridors and collect at least 5 comps per corridor × format from Grid's broker network and public listings. | F10: Corridors (proposal): Bacoor/Molino, Imus, Dasmariñas, General Trias/Tanza, Tagaytay, Batangas City, Lipa, Sto. Tomas/Tanauan. Capture template (format, corridor, base rent ₱/sqm, CUSA, escalation, term, observed_date, source) → lease.<region>.json → loadLease. Truth: Verified only for signed/confirmed leases, else Assumed. | G10: Real corridor benchmarks for the main provincial trade areas; proxy flag disappears for those sites. | H10: P2 | I10: L | J10: 07 Broker · 02 Database | K10: R-01
A11: R-07 | B11: Regional expansion | C11: Mall and traffic context missing for provinces | D11: mall_property has 33 NCR malls; traffic_corridor has 15 NCR/Davao corridors. Provincial sites get 'no mall nearby' and a POI-count traffic proxy. | E11: Seed malls from OSM (shop=mall) with broker-reviewed tier/footfall; add major provincial arterials with DPWH AADT as traffic corridors. | F11: Overpass shop=mall per province → review sheet (tier A/B/C, footfall band = Assumed) → malls.<region>.json → loadMalls. Traffic: DPWH AADT for e.g. Aguinaldo Hwy, Governor's Drive, Molino Blvd, SLEX/STAR Tollway, Batangas–Lipa roads → trafficSeasonality rows (Assumed). | G11: Mall and Land/Traffic modules score provincial sites on real context. | H11: P2 | I11: M | J11: 02 Database · 07 Broker | K11: R-02
A12: R-08 | B12: Regional expansion | C12: No regional QA pass | D12: Davao and NCR had 'brutal' QA runs; provinces have none. | E12: Run the scripted QA journey for 8–10 realistic Cavite/Batangas scenarios after data load. | F12: Copy scripts/qa_davao_brutal.ts → qa_calabarzon.ts (Imus milk tea, Dasmariñas pharmacy, Lipa QSR, Batangas City laundry, Tagaytay café…). Check: no proxy flags, Truth mix, confidence not Low by default, zero console errors. Record in docs/qa-history. | G12: Signed-off provincial journeys before brokers use Cavite/Batangas. | H12: P2 | I12: S | J12: 08 Journey QA · 11 Code QA | K12: R-01..R-07
A13: D-01 | B13: Data & scoring | C13: Site Fit 'accessibility' pillar is always empty | D13: The 15% accessibility pillar is null for every site (no transport layer), so Site Fit only uses demand + competition. | E13: Score access from OSM transport features (jeepney/bus stops, rail stations, main roads) within walking distance. | F13: Overpass: public_transport=platform|stop_position, railway=station, highway=primary|trunk within 500 m → poi category 'transport' (already in enum). siteFit.ts: access = f(stops within 400 m, station within 800 m, frontage on primary road). Unit tests. | G13: Site Fit uses all three pillars; access-rich sites score higher. | H13: P2 | I13: M | J13: 02 Database · 01 Senior Web | K13: R-03
A14: D-02 | B14: Data & scoring | C14: Trade areas are fixed circles | D14: Catchments are circles by format (600–1,200 m). Rivers, highways and gated villages make real walk/drive areas very different. | E14: Replace circles with travel-time isochrones for the candidate and nearby outlets. | F14: Self-host OSRM/Valhalla or use an isochrone API server-side; cache polygons per site in a new column; overlap = ST_Area(ST_Intersection). Keep circles as fallback. | G14: More realistic cannibalization and catchment population, especially in provinces. | H14: P3 | I14: L | J14: 02 Database · 06 Research | K14: R-02
A15: D-03 | B15: Data & scoring | C15: Lease comp set is thin and ages silently | D15: 80 comps across 15 corridors; most are Assumed; no freshness rule. | E15: Add a comp feedback loop: brokers submit confirmed rents; age comps out after 24 months. | F15: API POST /api/lease-comps (staff/broker, Zod, audit), observed_date required; benchmark filters to ≤24 months (configurable) and shows sample age. Admin review queue. | G15: Growing, dated, broker-verified comp set; fewer low-sample reads. | H15: P2 | I15: M | J15: 03 API · 02 Database · 07 Broker
A16: D-04 | B16: Data & scoring | C16: Known zonal gaps in NCR | D16: San Juan zonal values are missing entirely; Valenzuela barangay grain missing (the source folder held a Taguig duplicate). | E16: Obtain the correct BIR workbooks and re-run the zonal ETL. | F16: Download current RDO schedules for San Juan and Valenzuela → prisma/data/zonal.real.json → npm run db:populate:ncr. | G16: Complete NCR zonal coverage. | H16: P2 | I16: S | J16: 02 Database
A17: D-05 | B17: Data & scoring | C17: Google-sourced POIs recorded as 'manual' | D17: PoiSource enum has only osm | manual, so provenance of Places-ingested rows is lost. | E17: Add 'google' to PoiSource and a raw_tags/provenance JSON column. | F17: Prisma enum migration (ALTER TYPE ADD VALUE), update lib/ingest/places.ts, backfill where possible. | G17: Every POI's source is traceable (licensing + Truth Layer honesty). | H17: P3 | I17: S | J17: 02 Database
A18: D-06 | B18: Data & scoring | C18: Age profiles are modelled from income | D18: demographic_cell.age_profile is a Projected model from income band (used by Healthcare). | E18: Replace with PSA age-sex distribution by city/municipality. | F18: PSA 2020 CPH age tables → enrichAgeProfiles.ts reads real distribution; Truth Verified at city grain, Assumed when down-scaled to barangay. | G18: Healthcare catchment uses real age data. | H18: P3 | I18: M | J18: 02 Database | K18: R-04
A19: D-07 | B19: Data & scoring | C19: Old runs keep pre-fix scores | D19: Runs created before 23 Sep 2026 still show old confidence/labels until re-run; the dashboard keeps a legacy confidence fallback for them. | E19: Bulk re-run historical runs once migrations are applied, then remove the legacy fallback. | F19: Admin script scripts/rerunAll.ts (loops runPipeline(id,{refresh:true}) with pauses); then delete the fallback branch in lib/modules/dashboard.ts. | G19: All runs scored by one rule set; less legacy code for the dev team. | H19: P2 | I19: S | J19: 01 Senior Web
A20: I-01 | B20: AI layer | C20: VectorShift prompt not yet updated for the new input | D20: The app now sends the site schema + interpretation reference; the prompt inside VectorShift still says 'use ONLY the schema'. | E20: Add one line to the VectorShift prompt and version the prompt text in the repo. | F20: Prompt line: 'An INTERPRETATION REFERENCE may follow the schema — use it only to understand the fields; cite figures only from the schema.' Copy the live System + Prompt into lib/ai/prompts/vectorshift.v4.md with a version id logged on each generation. | G20: Prompt changes are reviewable in git; write-ups stay grounded. | H20: P1 | I20: S | J20: 10 AI Systems
A21: I-02 | B21: AI layer | C21: Live AI can exceed Netlify's function time limit | D21: Each site's write-up must finish inside one synchronous function (≤26 s). Slow model responses surface as 502 'function_timeout'. | E21: Move generation to a Netlify Background Function (runs up to 15 min) and let the UI poll the existing status endpoint. | F21: netlify/functions/analysis-background.ts calls generateAnalysisReport; POST /api/analysis-report enqueues and returns 202; the Analysis tab already polls GET /api/analysis-report. Keep the per-site lock. | G21: No AI timeouts regardless of model latency. | H21: P1 | I21: M | J21: 10 AI Systems · 03 API
A22: I-03 | B22: AI layer | C22: Semantic search (pgvector) is not used | D22: doc_chunk.embedding + HNSW index exist but retrieval is keyword-only; fine for 20 chunks, weak as the corpus grows. | E22: Add an embedding provider and hybrid (keyword + vector) retrieval. | F22: EMBEDDING_PROVIDER env; embed chunks at seed time; retrieve() = tsvector rank ⊕ cosine (<=>) with RRF merge; tests with a fixed corpus. | G22: Better grounding for the AI as methodology/market docs grow. | H22: P3 | I22: M | J22: 10 AI Systems · 02 Database
A23: I-04 | B23: AI layer | C23: No admin view of AI usage and cost | D23: pipeline_usage records cost, latency and failures but nothing displays it. | E23: Add an admin-only usage page. | F23: GET /api/admin/usage (isAdmin) aggregating by day/user/brand; /settings/usage page with totals, failure rate, p95 latency. | G23: Grid can monitor AI spend and reliability. | H23: P2 | I23: S | J23: 03 API · 01 Senior Web
A24: A-01 | B24: Architecture | C24: Pages read the database directly (not API-first) | D24: 7 server pages (intake, modules, reports, runs, scorecard, settings, site) plus the app layout query Prisma directly. Access checks are applied and nothing leaks, but it deviates from the API-first rule. | E24: Move page data loading behind lib/ services shared with the API routes (or call the routes). | F24: Create lib/services/{runs,sites,reports}.ts used by both routes and pages; pages stop importing prisma. | G24: One data-access path; easier production hardening and caching. | H24: P2 | I24: M | J24: 03 API · 01 Senior Web
A25: A-02 | B25: Architecture | C25: White-Space is O(areas × POIs) per site | D25: Every site loads all competitor POIs and all demographic cells and scores in JavaScript. Provinces will multiply the cost. | E25: Push tiering/counting into PostGIS and compute once per run. | F25: SQL with ST_DWithin + GROUP BY area; cache result per (run, concept); restrict to the site's region. | G25: White-Space stays fast as data grows. | H25: P2 | I25: M | J25: 02 Database | K25: R-01
A26: A-03 | B26: Architecture | C26: Reference-data loaders are row-by-row | D26: Loaders do find-then-write per row over Neon HTTP; a province-scale load will be slow and partial loads aren't atomic. | E26: Batch upserts (INSERT … ON CONFLICT) in chunks of 500 using the pooled/direct connection for scripts. | F26: Script-only PrismaClient on DIRECT_URL (not the HTTP adapter); $executeRaw batch upserts; per-dataset transaction. | G26: Province loads in minutes, all-or-nothing. | H26: P2 | I26: M | J26: 02 Database
A27: A-04 | B27: Architecture | C27: No automated end-to-end journey tests | D27: Unit tests (331) cover logic; the journey is only checked manually. Playwright is already a dev dependency. | E27: Add Playwright smoke tests for the core journey against a seeded preview database. | F27: tests/e2e: login → intake (demo prefill) → run → site tabs → Analysis (stub AI) → run report. Run in CI on a Neon branch. | G27: Regressions like the hydration error are caught before deploy. | H27: P2 | I27: M | J27: 11 Code QA · 08 Journey QA | K27: O-01
A28: A-05 | B28: Architecture | C28: Unused schema values | D28: ModuleKind values financial, risk, calibration are never written. | E28: Remove or document as reserved. | F28: Either a migration dropping them (Postgres enum rebuild) or a comment in schema.prisma + data dictionary. | G28: A schema the dev team can trust. | H28: P3 | I28: S | J28: 02 Database
A29: O-01 | B29: Operations | C29: No CI pipeline | D29: Typecheck, tests and build only run when someone runs them. | E29: GitHub Actions on every push/PR. | F29: .github/workflows/ci.yml: npm ci → prisma generate → npm run typecheck → npm test → npm run build; npm audit (fail on high). | G29: Broken code can't reach main unnoticed. | H29: P1 | I29: S | J29: 11 Code QA
A30: O-02 | B30: Operations | C30: Migrations are applied by hand | D30: Every batch needed a manual 'prisma migrate deploy'; forgetting it caused the analysis 502s. | E30: Apply migrations automatically on deploy (or block the deploy if pending). | F30: Netlify build: npx prisma migrate deploy && npx prisma generate && npm run build (DIRECT_URL set in Netlify), or a CI step before deploy. | G30: Code and database can't drift apart. | H30: P1 | I30: S | J30: 02 Database · 12 Delivery
A31: O-03 | B31: Operations | C31: Single environment | D31: Local and production point at the same Neon database. | E31: Separate dev / preview / production using Neon branches and Netlify deploy contexts. | F31: Neon branch per environment; Netlify env vars per context; preview deploys use a preview branch. | G31: Testing never touches production data. | H31: P1 | I31: S | J31: 12 Delivery · 04 Security
A32: O-04 | B32: Operations | C32: No error monitoring | D32: Server errors only appear in Netlify function logs. | E32: Add error tracking and structured logs. | F32: Sentry (or similar) for Next.js server + client; log request id + reason codes already produced by the API. | G32: Problems are seen and triaged before users report them. | H32: P2 | I32: S | J32: 12 Delivery
A33: S-01 | B33: Security | C33: Rotate exposed credentials | D33: The Google API key in keys.docx is exposed; real account passwords were in the old public database dump. | E33: Rotate the key (restrict by API + referrer) and reset affected passwords. | F33: Google Cloud console → new key → GOOGLE_API_KEY in Netlify; revoke old. Force password reset for accounts that existed before 23 Sep. | G33: No known-compromised credentials remain. | H33: P1 | I33: S | J33: 04 Security
A34: S-02 | B34: Security | C34: CSP still allows inline scripts | D34: Next 14 needs 'unsafe-inline' for its bootstrap scripts. | E34: Nonce-based CSP via middleware. | F34: middleware.ts generates a nonce per request, sets CSP header, passes nonce to next/script. | G34: Stronger XSS protection. | H34: P2 | I34: M | J34: 04 Security
A35: S-03 | B35: Security | C35: Sessions can't be revoked | D35: JWTs are valid for 8 h even after logout or a password change. | E35: Add a token version to app_user and check it on each request. | F35: app_user.token_version; increment on logout-all/password change; verifySession compares. | G35: Logout and password change take effect immediately. | H35: P2 | I35: S | J35: 04 Security
A36: S-04 | B36: Security | C36: Rate limiting only in the app | D36: The DB-backed limiter works but runs after the request reaches the function. | E36: Add edge/WAF rate limits for /api/auth/*. | F36: Netlify rate-limit rules or a CDN WAF in front of the site. | G36: Brute-force traffic stopped before it costs compute. | H36: P3 | I36: S | J36: 04 Security
A37: U-01 | B37: User experience | C37: No navigation on mobile | D37: The sidebar is hidden below the md breakpoint and the mobile header only has 'BSA' and Logout — a broker on a phone can't reach Intake, Screening or Reports. | E37: Add a mobile menu (drawer) using the same SidebarNav items. | F37: components/MobileNav.tsx (button + slide-over), rendered in app/(app)/layout.tsx header; test at 375 px. | G37: Field brokers can use BSA fully on a phone. | H37: P1 | I37: S | J37: 01 Senior Web · 07 Broker
A38: U-02 | B38: User experience | C38: Proxy corridor can't be corrected by the user | D38: When no corridor matches, the Lease tab says it's a proxy but offers no way to pick the right corridor. | E38: Add a corridor picker on the Lease tab (list from lease_comp corridors for the site's region). | F38: GET /api/lease-benchmark/corridors?region=; select on LeaseTab; re-benchmark via existing POST. | G38: Brokers fix the benchmark themselves instead of getting a proxy. | H38: P2 | I38: S | J38: 01 Senior Web · 03 API | K38: R-01
A39: U-03 | B39: User experience | C39: Territory map ring colour can lag the verdict | D39: Noted in QA: the map ring uses the map component's own verdict and can show green while the stats say 'Redistributes'. | E39: Pass the blended verdict into TerritoryMap. | F39: One prop change in SiteIntelligenceTabs → TerritoryMap. | G39: Map and verdict always agree. | H39: P2 | I39: S | J39: 01 Senior Web
A40: U-04 | B40: User experience | C40: Stale AI write-up after saving an asking rent | D40: Saving a rent updates the score, but the cached write-up still describes the old lease read (the user is told to regenerate). | E40: Mark the analysis stale when module results change and offer a one-click refresh (not counted against the regenerate cap). | F40: On lease save / re-run, set analysis payload.stale = true; Analysis tab shows a 'Figures changed — refresh' banner; generation with reason 'stale' bypasses the cap. | G40: The write-up never contradicts the numbers on screen. | H40: P2 | I40: S | J40: 10 AI Systems · 01 Senior Web

Sheet Cavite-Batangas Data Plan
A1: Expanding BSA to Cavite & Batangas — getting the data (Overpass API + official sources) into Neon Postgres
A2: OpenStreetMap via the Overpass API gives establishments, malls, transport and (partly) barangay boundaries/populations. Population, zonal values, lease comps and traffic come from official or broker sources. Every step writes to the existing Neon tables through idempotent loaders, keeps its Truth Layer, and is re-runnable. Overpass is a shared free service: stay under ~10,000 queries and ~1 GB per day, run sequentially with pauses, and credit OpenStreetMap (ODbL).
A4: Step | B4: Phase | C4: What | D4: Source / API | E4: How (method) | F4: Implementation needed | G4: Neon table(s) written | H4: Truth Layer | I4: Done when (desired outcome)
A5: 1 | B5: 0 · Prepare | C5: Region registry + schema columns | D5: — | E5: Define Cavite and Batangas once: PSGC province codes, bounding boxes, Overpass area names, warm-grid centres, corridor names. | F5: lib/geo/regions.ts (see Backlog R-01). Migration: add region, province, psgc_code to poi, candidate_site, mall_property; add admin_boundary table (R-02). CLI flag --region=cavite|batangas on ingest scripts. | G5: (schema only) | H5: — | I5: npx prisma migrate deploy applies cleanly on Neon; npm run typecheck passes.
A6: 2 | B6: 1 · Boundaries | C6: Barangay / city / province polygons | D6: PSGC shapefiles (altcoder/philippines-psgc-shapefiles, PSGC Q4-2023, MIT). Cross-check: OSM boundary=administrative, admin_level=4 (province) / 10 (barangay). | E6: Download PH_Adm2/Adm3/Adm4 shapefiles; filter to Cavite and Batangas by PSGC province code; convert to GeoJSON (ogr2ogr) and load. Use OSM relations only to fill gaps. | F6: prisma/loadBoundaries.ts --region=… : read GeoJSON → INSERT … ON CONFLICT (psgc_code) with ST_GeomFromGeoJSON → GiST index. Verify counts vs PSA barangay lists. | G6: admin_boundary | H6: Verified (official PSGC) | I6: Every Cavite/Batangas barangay has a polygon; ST_Contains returns one barangay for any point in the province.
A7: 3 | B7: 2 · Establishments (Overpass) | C7: Competitor POIs for all 20 verticals | D7: Overpass API (overpass-api.de + 2 mirrors already configured) | E7: Query per province area (area["admin_level"="4"]["name"=…]) or per tile inside the province bbox; one vertical per query; out center; adaptive split when a tile hits the result cap. 2.5 s pause between calls; resume from poi_coverage checkpoints. | F7: Extend prisma/ingestOsm.ts: --region, tile loop (R-03), write via loadPoi (upsert on osm_id), stamp poi_coverage(source='bulk'). Then SQL snap: UPDATE poi SET barangay/city/province/psgc_code FROM admin_boundary WHERE ST_Contains(geom, poi.geom). | G7: poi, poi_coverage | H7: Verified (coordinates) · category mapping Assumed | I7: Per-vertical counts logged per tile; no tile at the cap; POIs carry barangay + city.
A8: 4 | B8: 2 · Establishments (Overpass) | C8: Brand branches (≈70 chains) | D8: Overpass API — brand / name / brand:wikidata tags | E8: Run the existing BRAND_PULL list against each province area. | F8: ingestOsm.ts --region=… --brands (existing brandBranchesInBbox, bbox → region). | G8: poi | H8: Verified (coordinates) | I8: Known chains (Jollibee, Mercury Drug, 7-Eleven, Puregold…) mapped in both provinces.
A9: 5 | B9: 2 · Establishments (Overpass) | C9: Transport + anchors for access/traffic proxies | D9: Overpass: public_transport, railway=station, amenity=bus_station, office=*, shop=mall | E9: One sweep per category per province (lower density → fewer tiles). | F9: osmService selectors for transport/office/mall already exist → categories 'transport', 'office', 'mall'. Feeds D-01 accessibility pillar and the Land traffic fallback. | G9: poi | H9: Verified | I9: Transport and office anchors present; Land module no longer 'unknown traffic' in town centres.
A10: 6 | B10: 3 · Malls | C10: Mall list with tier + footfall | D10: Overpass shop=mall (names + coordinates) + broker review | E10: Pull malls, export a review sheet, broker assigns tier (A/B/C) and footfall band, then load. | F10: scripts/exportMalls.ts --region=… → CSV → reviewed → prisma/data/malls.<region>.json → loadMalls (upsert on name + city). | G10: mall_property | H10: Coordinates Verified · tier/footfall Assumed | I10: Mall module scores Cavite/Batangas sites within 3 km of a mall.
A11: 7 | B11: 4 · Demographics | C11: Barangay population (and estimated bands) | D11: PSA 2020 Census of Population & Housing (Region IV-A barangay tables). Cross-check: OSM place nodes with population=* and ref (PSGC). | E11: Match PSA rows to admin_boundary by PSGC code; add income band (PSA FIES/regional proxies) and daytime population estimates as Assumed. | F11: ETL → prisma/data/demographics.<region>.json (psgc_code, barangay, city, population, income_band, daytime_pop, truth_layer per field) → loadDemographics with geom from admin_boundary (replaces the 600 m circle). | G11: demographic_cell | H11: Population Verified · bands Assumed | I11: Site Fit, Daypart and White-Space score provincial sites; confidence no longer forced Low.
A12: 8 | B12: 5 · Zonal values | C12: BIR zonal values | D12: BIR zonal schedules — RDO 54A (Trece Martires, East Cavite), RDO 54B (Bacoor, West Cavite), RDO 58 & 59 (Batangas) | E12: Download the latest schedules; run the NCR zonal ETL (label canonicalisation, ₱ parsing, barangay + city grain). | F12: Generalise the zonal ETL (--region); canonicalCity for provincial LGUs; loadZonal (natural key region+city+barangay+rdo+class). | G12: zonal_value | H12: Verified (BIR) — tax-reference floor only | I12: Zonal band + cross-check shown for provincial sites; zoning screen not 'unknown'.
A13: 9 | B13: 6 · Lease comps | C13: Corridor rent comparables | D13: Grid broker network · public listings (verify) · signed leases | E13: Collect ≥5 comps per corridor × format; record observed_date and source. | F13: Capture template → prisma/data/lease.<region>.json → loadLease; add corridors to the region registry + inferCorridor(region). | G13: lease_comp | H13: Verified only for confirmed leases · else Assumed | I13: Lease Benchmark uses local corridors; proxy flag gone for covered corridors.
A14: 10 | B14: 7 · Traffic | C14: Arterial traffic bands | D14: DPWH AADT counts; seasonal multipliers per existing model | E14: Add the main provincial arterials as corridors with AADT-anchored bands. | F14: Append rows to prisma/data/trafficSeasonality.real.json → npm run db:seed-traffic. | G14: traffic_corridor | H14: Assumed (AADT-anchored) | I14: Land & Traffic uses corridor bands for key roads.
A15: 11 | B15: 8 · Wire up | C15: Resolvers, warm grid, UI | D15: — | E15: Make runtime lookups region-aware and pre-warm the on-demand cache for busy provincial centres. | F15: inferCorridor/canonicalCity by region; region warm centres (e.g. Imus, Dasmariñas, Bacoor, General Trias, Tagaytay, Batangas City, Lipa, Sto. Tomas); /api/admin/warm accepts area:'cavite'|'batangas'. | G15: poi_coverage | H15: — | I15: A new Cavite/Batangas site loads without cold-cache delays.
A16: 12 | B16: 9 · Validate | C16: Data checks + journey QA | D16: — | E16: Run validators and scripted journeys; compare counts to known totals. | F16: npm run db:validate (extend with per-region checks: barangays with population, POIs per 10k people, comps per corridor); qa_calabarzon.ts (Backlog R-08). | G16: — | H16: — | I16: Validation report clean; QA scenarios pass; results logged in WORKLOG.

Sheet Overpass Query Templates
A1: Overpass QL templates (to be wrapped by lib/places/osmService.ts)
A2: Test any query at overpass-turbo.eu first. Keep [timeout:90]; one vertical per query; sequential runs with ~2.5 s pauses (already the ingest default). Replace {BBOX} with south,west,north,east of a tile.
A4: Purpose | B4: Overpass QL | C4: Notes | D4: Maps to
A5: Province area handle (Cavite) | B5: [out:json][timeout:90]; area["boundary"="administrative"]["admin_level"="4"]["name"="Cavite"]->.prov; nwr["amenity"~"^(fast_food|restaurant|cafe)$"](area.prov); out center 2000; | C5: Province = admin_level 4 in OSM Philippines. Use name="Batangas" for Batangas. Area queries are simplest but can time out for dense categories — prefer tiles for food/retail. | D5: poi (competitor)
A6: Tiled sweep (preferred for dense verticals) | B6: [out:json][timeout:90]; ( nwr["amenity"="pharmacy"]({BBOX}); nwr["healthcare"="pharmacy"]({BBOX}); ); out center 600; | C6: Tile ~0.05°–0.1°. If the result count equals the limit, split the tile into 4 and re-query. Clip results to the province polygon in SQL afterwards. | D6: poi (competitor)
A7: Brand branches | B7: [out:json][timeout:90]; area["admin_level"="4"]["name"="Batangas"]->.prov; nwr["brand"~"Jollibee",i](area.prov); nwr["name"~"Jollibee",i](area.prov); out center 300; | C7: Same pattern as the existing BRAND_PULL; add brand:wikidata where known for precision. | D7: poi (competitor)
A8: Malls | B8: [out:json][timeout:90]; area["admin_level"="4"]["name"="Cavite"]->.prov; nwr["shop"="mall"](area.prov); out center; | C8: Export for broker tier/footfall review before loading. | D8: mall_property
A9: Transport anchors | B9: [out:json][timeout:90]; area["admin_level"="4"]["name"="Cavite"]->.prov; ( nwr["public_transport"="station"](area.prov); nwr["amenity"="bus_station"](area.prov); nwr["railway"="station"](area.prov); ); out center; | C9: Feeds the Site Fit accessibility pillar (Backlog D-01) and the Land traffic fallback. | D9: poi (transport)
A10: Barangay boundaries (cross-check) | B10: [out:json][timeout:180]; area["admin_level"="4"]["name"="Batangas"]->.prov; rel["boundary"="administrative"]["admin_level"="10"](area.prov); out geom; | C10: Barangay = admin_level 10 (admin_type:PH=barangay). OSM coverage is uneven outside Metro Manila — use PSGC shapefiles as the primary source. | D10: admin_boundary (gap-fill)
A11: Barangay place nodes with population (cross-check) | B11: [out:json][timeout:90]; area["admin_level"="4"]["name"="Cavite"]->.prov; node["place"]["population"](area.prov); out; | C11: PH mapping convention adds population + PSGC ref to barangay place nodes where mapped. Use only to sanity-check PSA figures. | D11: demographic_cell (QA only)

Sheet Data Coverage Matrix
A1: Reference data coverage by area (today) and where the missing data comes from
A3: Dataset | B3: Neon table | C3: NCR | D3: Davao | E3: Cavite | F3: Batangas | G3: Source to fill gaps | H3: Truth Layer when loaded
A4: Establishments / competitors | B4: poi | C4: Bulk NCR sweep + on-demand cache (capped per query) | D4: Partial (populate --region=davao) | E4: On-demand cache only (per report, ~1 km cells) | F4: On-demand cache only | G4: Overpass tiled sweep (Plan steps 3–5) | H4: Verified coordinates
A5: Administrative boundaries | B5: (new) admin_boundary | C5: None — 600 m circles | D5: None | E5: None | F5: None | G5: PSGC shapefiles; OSM admin_level 4/10 cross-check | H5: Verified
A6: Demographics | B6: demographic_cell | C6: 283 barangays (Assumed) | D6: 13 cells | E6: None | F6: None | G6: PSA 2020 CPH barangay tables | H6: Population Verified · bands Assumed
A7: BIR zonal values | B7: zonal_value | C7: 2,317 rows (San Juan + Valenzuela bgy missing) | D7: None | E7: None | F7: None | G7: BIR RDO 54A / 54B | H7: BIR RDO 58 / 59
A8: Lease comparables | B8: lease_comp | C8: ~15 corridors, 80 comps (NCR + Davao) | D8: Included in the 15 | E8: None (Bacoor → Las Piñas proxy; else QC proxy) | F8: None (QC proxy) | G8: Broker network + confirmed leases | H8: Verified if confirmed · else Assumed
A9: Malls | B9: mall_property | C9: 33 NCR malls | D9: None | E9: None | F9: None | G9: Overpass shop=mall + broker tiering | H9: Coords Verified · tier Assumed
A10: Traffic corridors | B10: traffic_corridor | C10: NCR corridors (of 15) | D10: Davao corridors (of 15) | E10: None | F10: None | G10: DPWH AADT | H10: Assumed
A11: Competitor sets | B11: competitor_set | C11: National (89 anchors) | D11: National | E11: National | F11: National | G11: — | H11: As loaded
A12: Franchise requirements | B12: franchisor.requirements | C12: National (161 brands) | D12: National | E12: National | F12: National | G12: — | H12: As loaded
A15: Note: 'None' means sites there fall back to proxies (flagged Projected in the app) or leave the module unscored.

Sheet Sources
A1: Sources
A3: Topic | B3: Reference | C3: Used for
A4: Overpass usage guidance | B4: https://dev.overpass-api.de/overpass-doc/en/preface/commons.html | C4: ~10,000 requests/day and ~1 GB/day guideline; run own instance if more is needed
A5: OSM PH barangay tagging | B5: https://wiki.openstreetmap.org/wiki/Tag:admin_type:PH=barangay | C5: Barangay = admin_level 10; optional population and PSGC ref tags
A6: OSM PH mapping conventions | B6: https://wiki.openstreetmap.org/wiki/Philippines/Mapping_conventions | C6: Province = admin_level 4 boundaries
A7: PSGC boundary shapefiles | B7: https://github.com/altcoder/philippines-psgc-shapefiles | C7: Region/province/city/barangay polygons (PSGC Q4-2023, MIT licence)
A8: PSA 2020 CPH — CALABARZON | B8: https://psa.gov.ph/content/highlights-region-iv-calabarzon-population-2020-census-population-and-housing-2020-cph | C8: Cavite 4,344,829 and Batangas 2,908,494 (2020); barangay tables for demographics
A9: BIR zonal values | B9: https://www.bir.gov.ph/zonal-values | C9: Schedules for RDO 54A, 54B (Cavite) and 58, 59 (Batangas)
A10: RDO 54 split (54A / 54B) | B10: https://www.scribd.com/document/412950747/RDO-No-54B-Bacoor-City-West-Cavite | C10: Which Cavite LGUs fall under each RDO (verify against the BIR page)
A11: OpenStreetMap licence | B11: https://www.openstreetmap.org/copyright | C11: ODbL attribution required wherever OSM-derived data is shown
A12: Internal | B12: 4 - Final Application: WORKLOG.md, PROJECT_MEMORY.md, docs/HANDOFF.md, docs/SECURITY_POSTURE.md | C12: Open items from the 23 Sep 2026 review and fix batches 1–5
