Workbook

Sheet Summary
A1: BSA v3 — Application Audit
A2: GRID Property Ventures · Business Site Analysis · audited 25 Sep 2026 (after the AI removal and brand update)
A4: Findings by area and severity
A5: Area | B5: High | C5: Medium | D5: Low | E5: Total | F5: Done
A6: Stability & bugs | B6: =COUNTIFS('Audit Findings'!$B$5:$B$56,$A6,'Audit Findings'!$C$5:$C$56,"High") -> 4 | C6: =COUNTIFS('Audit Findings'!$B$5:$B$56,$A6,'Audit Findings'!$C$5:$C$56,"Medium") -> 2 | D6: =COUNTIFS('Audit Findings'!$B$5:$B$56,$A6,'Audit Findings'!$C$5:$C$56,"Low") -> 0 | E6: =SUM(B6:D6) -> 6 | F6: =COUNTIFS('Audit Findings'!$B$5:$B$56,$A6,'Audit Findings'!$M$5:$M$56,"Done") -> 4
A7: Data & scoring | B7: =COUNTIFS('Audit Findings'!$B$5:$B$56,$A7,'Audit Findings'!$C$5:$C$56,"High") -> 3 | C7: =COUNTIFS('Audit Findings'!$B$5:$B$56,$A7,'Audit Findings'!$C$5:$C$56,"Medium") -> 7 | D7: =COUNTIFS('Audit Findings'!$B$5:$B$56,$A7,'Audit Findings'!$C$5:$C$56,"Low") -> 3 | E7: =SUM(B7:D7) -> 13 | F7: =COUNTIFS('Audit Findings'!$B$5:$B$56,$A7,'Audit Findings'!$M$5:$M$56,"Done") -> 1
A8: Performance | B8: =COUNTIFS('Audit Findings'!$B$5:$B$56,$A8,'Audit Findings'!$C$5:$C$56,"High") -> 1 | C8: =COUNTIFS('Audit Findings'!$B$5:$B$56,$A8,'Audit Findings'!$C$5:$C$56,"Medium") -> 2 | D8: =COUNTIFS('Audit Findings'!$B$5:$B$56,$A8,'Audit Findings'!$C$5:$C$56,"Low") -> 1 | E8: =SUM(B8:D8) -> 4 | F8: =COUNTIFS('Audit Findings'!$B$5:$B$56,$A8,'Audit Findings'!$M$5:$M$56,"Done") -> 0
A9: Security | B9: =COUNTIFS('Audit Findings'!$B$5:$B$56,$A9,'Audit Findings'!$C$5:$C$56,"High") -> 1 | C9: =COUNTIFS('Audit Findings'!$B$5:$B$56,$A9,'Audit Findings'!$C$5:$C$56,"Medium") -> 6 | D9: =COUNTIFS('Audit Findings'!$B$5:$B$56,$A9,'Audit Findings'!$C$5:$C$56,"Low") -> 1 | E9: =SUM(B9:D9) -> 8 | F9: =COUNTIFS('Audit Findings'!$B$5:$B$56,$A9,'Audit Findings'!$M$5:$M$56,"Done") -> 0
A10: UX & accessibility | B10: =COUNTIFS('Audit Findings'!$B$5:$B$56,$A10,'Audit Findings'!$C$5:$C$56,"High") -> 2 | C10: =COUNTIFS('Audit Findings'!$B$5:$B$56,$A10,'Audit Findings'!$C$5:$C$56,"Medium") -> 8 | D10: =COUNTIFS('Audit Findings'!$B$5:$B$56,$A10,'Audit Findings'!$C$5:$C$56,"Low") -> 0 | E10: =SUM(B10:D10) -> 10 | F10: =COUNTIFS('Audit Findings'!$B$5:$B$56,$A10,'Audit Findings'!$M$5:$M$56,"Done") -> 2
A11: Code health | B11: =COUNTIFS('Audit Findings'!$B$5:$B$56,$A11,'Audit Findings'!$C$5:$C$56,"High") -> 0 | C11: =COUNTIFS('Audit Findings'!$B$5:$B$56,$A11,'Audit Findings'!$C$5:$C$56,"Medium") -> 3 | D11: =COUNTIFS('Audit Findings'!$B$5:$B$56,$A11,'Audit Findings'!$C$5:$C$56,"Low") -> 3 | E11: =SUM(B11:D11) -> 6 | F11: =COUNTIFS('Audit Findings'!$B$5:$B$56,$A11,'Audit Findings'!$M$5:$M$56,"Done") -> 0
A12: Operations | B12: =COUNTIFS('Audit Findings'!$B$5:$B$56,$A12,'Audit Findings'!$C$5:$C$56,"High") -> 3 | C12: =COUNTIFS('Audit Findings'!$B$5:$B$56,$A12,'Audit Findings'!$C$5:$C$56,"Medium") -> 2 | D12: =COUNTIFS('Audit Findings'!$B$5:$B$56,$A12,'Audit Findings'!$C$5:$C$56,"Low") -> 0 | E12: =SUM(B12:D12) -> 5 | F12: =COUNTIFS('Audit Findings'!$B$5:$B$56,$A12,'Audit Findings'!$M$5:$M$56,"Done") -> 3
A13: Total | B13: =SUM(B6:B12) -> 14 | C13: =SUM(C6:C12) -> 30 | D13: =SUM(D6:D12) -> 8 | E13: =SUM(E6:E12) -> 52 | F13: =SUM(F6:F12) -> 10
A15: Do these first (highest impact, mostly small effort)
A16: 1. F-01 / F-02 — remove the remaining transaction-prone queries (same crash as the old AI report)
A17: 2. F-03 — delete the leftover calls to the removed AI endpoint (404s and a fake 'writing' step)
A18: 3. F-07 — make the dashboard verdict and the Final Report recommendation always agree
A19: 4. F-49 / F-50 — auto-apply migrations on deploy and show the running build id
A20: 5. F-48 — CI on every push
A21: 6. F-32 / F-33 — mobile navigation and an accurate onboarding tour
A22: 7. F-04 — keep each pipeline slice inside the time limit
A23: 8. F-31 — rotate the exposed Google key and passwords
A24: 9. F-19 — run the Cavite/Batangas data loads, then re-test
A25: 10. F-42 / F-52 — remove leftover AI code and update the docs for handoff
A27: How to use this workbook
... A34: • Evidence was confirmed in the code on 25 Sep 2026; line numbers can drift as files change.

Sheet Audit Findings
A1: Audit Findings
A2: Edit the Status column (drop-down) as work progresses. Priority is calculated from Severity.
A4: ID | B4: Area | C4: Severity | D4: Priority | E4: Problem | F4: Cause | G4: How to implement | H4: Desired result | I4: Evidence (file:line) | J4: Effort | K4: Owner | L4: Source | M4: Status
A5: F-01 | B5: Stability & bugs | C5: High | D5: =IF(C5="High","P1",IF(C5="Medium","P2","P3")) -> P1 | E5: The analysis pipeline can crash with "Transactions are not supported in HTTP mode" — the same error that broke the AI report. | F5: lib/modules/orchestrator.ts loads the run with findUniqueOrThrow + include (sites, franchisor, intake). Under the Neon HTTP adapter Prisma runs that as an implicit transaction, which HTTP mode rejects. | G5: Replace with findUnique (flat select) + explicit null check, then read sites / franchisor / intake with separate flat queries. Add a lint rule or test that bans findUniqueOrThrow/findFirstOrThrow combined with include on request paths. | H5: Running or re-running an intake never fails on the database adapter; one consistent data-access pattern across the app. | I5: lib/modules/orchestrator.ts:80 | J5: S | K5: Dev team | L5: New audit | M5: Done
A6: F-02 | B6: Stability & bugs | C6: High | D6: =IF(C6="High","P1",IF(C6="Medium","P2","P3")) -> P1 | E6: The run report, full report and scorecard builders use the same transaction-prone query. | F6: lib/modules/reportComposer.ts uses findUniqueOrThrow with include: { franchisor } on POST /api/reports, /api/reports/full and buildScorecards. | G6: Same fix as F-01: flat findUnique + separate franchisor read + null check. | H6: Run Report and PDF exports generate reliably on Netlify + Neon. | I6: lib/modules/reportComposer.ts:206 | J6: S | K6: Dev team | L6: New audit | M6: Done
A7: F-03 | B7: Stability & bugs | C7: High | D7: =IF(C7="High","P1",IF(C7="Medium","P2","P3")) -> P1 | E7: "Re-run analysis" and New Intake submit still call the deleted AI endpoint, fire a 404 per site and show a fake "Writing analyses…" step. | F7: When the AI report was removed, the client loops that POST /api/analysis-report after each run were left in place; errors are swallowed by .catch(() => null). | G7: Delete the analysis-report loops and the "writing" phase in RunPipelineButton and SteppedIntakeWizard; update the button tooltip copy. | H7: Re-run and submit finish as soon as the modules finish; no wasted requests or misleading status text. | I7: components/RunPipelineButton.tsx:33-56; components/SteppedIntakeWizard.tsx:370 | J7: S | K7: Dev team | L7: New audit | M7: Done
A8: F-04 | B8: Stability & bugs | C8: High | D8: =IF(C8="High","P1",IF(C8="Medium","P2","P3")) -> P1 | E8: One pipeline slice can outlive the serverless time limit, and a killed site is retried forever. | F8: The time budget is only checked between sites; each site can spend up to ~4.5 s warming the POI cache twice (orchestrator + Territory Guard) plus White-Space. The run route sets no maxDuration. analyzedAt is never written when the function is killed. | G8: Set export const maxDuration on /api/runs/[id]/run; warm the POI cache once per site and pass the result to Territory Guard; add an attempt counter on candidate_site and mark the site failed after N attempts. | H8: Every slice returns inside the platform limit; stuck sites fail clearly instead of looping. | I8: lib/modules/orchestrator.ts:131,150; lib/modules/territoryGuard.ts:330; lib/places/poiCache.ts:125; app/api/runs/[id]/run/route.ts | J8: M | K8: Dev team | L8: New audit | M8: Done
A9: F-05 | B9: Stability & bugs | C9: Medium | D9: =IF(C9="High","P1",IF(C9="Medium","P2","P3")) -> P2 | E9: Two browser tabs (or a double click) can process the same pending sites at the same time. | F9: The orchestrator picks pending sites with a plain read; nothing claims them before processing. | G9: Claim each site with a conditional updateMany (e.g. set processing_started_at where analyzed_at is null and not recently claimed) and skip sites whose claim fails. | H9: Each site is analysed exactly once per run; no duplicated work or racing writes. | I9: lib/modules/orchestrator.ts:117-128 | J9: M | K9: Dev team | L9: New audit | M9: Open
A10: F-06 | B10: Stability & bugs | C10: Medium | D10: =IF(C10="High","P1",IF(C10="Medium","P2","P3")) -> P2 | E10: A rejected or failed intake leaves orphan brands and half-written runs. | F10: For independent businesses the franchisor row is created before the 80% completeness check; intake, outlets, run and sites are then written one by one with no cleanup (no transactions on Neon HTTP). | G10: Run all validation and the completeness gate before any write; wrap the write sequence in try/catch with compensating deletes (or use a pooled client for this route). | H10: A failed submit leaves the database unchanged; no stray brands in Franchise Screening. | I10: app/api/intake/route.ts:52,86,219 | J10: M | K10: Dev team | L10: New audit | M10: Open
A11: F-07 | B11: Data & scoring | C11: High | D11: =IF(C11="High","P1",IF(C11="Medium","P2","P3")) -> P1 | E11: The Site Dashboard verdict and the Final Report recommendation can disagree for the same site. | F11: The dashboard uses the weighted composite score (scorecard.ts: Go ≥65, Caution ≥45, Site Fit 30%, capped when Site Fit is missing). The Final Report/PDF use summariseSite, which reads only Territory, Lease and Daypart with different Daypart cut-offs (60/40). | G11: Make one source of truth: feed the composite band into summariseSite so the recommendation can never be better than the scorecard band (or add Site Fit to summariseSite with the same weights). Add a unit test asserting the two always agree. | H11: A broker sees the same Proceed / Caution / No-Go call on the dashboard, the Final Report and the PDF. | I11: lib/modules/scorecard.ts:40-42,102; lib/modules/siteVerdict.ts:87-144 | J11: M | K11: Dev team | L11: New audit | M11: Done
A12: F-08 | B12: Data & scoring | C12: High | D12: =IF(C12="High","P1",IF(C12="Medium","P2","P3")) -> P1 | E12: Provincial lease reads use an NCR-only rent-to-land calibration and NCR wording. | F12: The ₱6–14 per ₱1,000 zonal band and the "typical NCR band" text were calibrated on NCR corridors but are applied to Davao, Cavite and Batangas zonal values. | G12: Store a calibration band per region in the region registry; return 'unknown' and hide the cross-check when a region has none; make the note text region-aware. | H12: Provincial rent-to-land cross-checks are either calibrated for that region or honestly withheld. | I12: lib/modules/leaseMath.ts:272-331; lib/modules/leaseBenchmark.ts:180-182 | J12: M | K12: Dev team | L12: New audit | M12: Open
A13: F-09 | B13: Data & scoring | C13: Medium | D13: =IF(C13="High","P1",IF(C13="Medium","P2","P3")) -> P2 | E13: Several code paths still silently default to NCR. | F13: Lease falls back to the Quezon City corridor for any region; zonal lookups default to 'NCR'; ingest sweeps default to the NCR grid. | G13: Resolve the fallback corridor per region from the registry; return null / 'no data' when a region has no zonal rows; require --region on ingest scripts. | H13: A Cavite or Batangas site is never scored against Metro Manila data without a clear flag. | I13: lib/modules/orchestrator.ts:55,176; lib/modules/p2p3Modules.ts:282; lib/modules/leaseBenchmark.ts:62; lib/geo/zonalRow.ts:39; lib/ingest/places.ts:231,324,403,461 | J13: M | K13: Dev team | L13: New audit | M13: Open
A14: F-10 | B14: Data & scoring | C14: Medium | D14: =IF(C14="High","P1",IF(C14="Medium","P2","P3")) -> P2 | E14: Some modules report a value when they actually have no data. | F14: Daypart's last-resort nearest demographic cell has no distance cap (can borrow another region's cell); a silently failed OSM warm returns 0 competitors, so Informal scores a perfect 100; Healthcare uses cnt ?? 0. | G14: Cap the nearest-cell fallback (e.g. 5 km); propagate a 'coverage unknown' flag from the POI cache and return null scores when coverage failed; treat missing counts as null, not 0. | H14: Missing data shows as "—" / low confidence, never as a strong score (Truth Layer rule). | I14: lib/modules/p2p3Modules.ts:66-70,142,173; lib/places/poiCache.ts:129,186 | J14: M | K14: Dev team | L14: New audit | M14: Open
A15: F-11 | B15: Data & scoring | C15: Medium | D15: =IF(C15="High","P1",IF(C15="Medium","P2","P3")) -> P2 | E15: White-Space can recommend barangays in another region (e.g. Davao areas for an NCR site). | F15: The White-Space ranking has no region or distance limit. | G15: Filter candidate areas by the site's region and a maximum distance (e.g. ST_DWithin 10–15 km). | H15: White-Space suggestions are always local and actionable for the broker. | I15: lib/modules/p2p3Math.ts:387-389 | J15: S | K15: Dev team | L15: New audit | M15: Open
A16: F-12 | B16: Data & scoring | C16: Medium | D16: =IF(C16="High","P1",IF(C16="Medium","P2","P3")) -> P2 | E16: The schema allows duplicate or colliding reference data. | F16: mall_property has no unique key but is upserted by mall name (same-name malls in different regions overwrite each other); lease_comp has no natural key; demographic_cell has no region column. | G16: Add region to mall_property + unique (region, mall_name); add a natural key to lease_comp; add region to demographic_cell (backfill from admin_boundary); update the loaders. | H16: Loading one province can never overwrite another's malls or comps; region-scoped reads become cheap. | I16: prisma/schema.prisma:398-457; lib/ingest/loaders.ts:185 | J16: M | K16: Dev team | L16: New audit | M16: Open
... A56: F-52 | B56: Operations | C56: Medium | D56: =IF(C56="High","P1",IF(C56="Medium","P2","P3")) -> P2 | E56: The documentation is out of date for the handoff. | F56: README, HANDOFF, API_REFERENCE and DATA_DICTIONARY still describe the VectorShift analysis endpoint; the .env.example demo account doesn't match the code; the new Proceed/Caution/No-Go rules aren't documented. | G56: Update the docs; add a 'How the recommendation is decided' section (siteVerdict rules + scorecard bands) and the regional data-load runbook. | H56: The dev team can onboard from the docs alone. | I56: README.md:22,60; docs/HANDOFF.md:42,63,100; docs/API_REFERENCE.md:165-169; docs/DATA_DICTIONARY.md:122; .env.example | J56: S | K56: Dev team | L56: New audit | M56: Open

Sheet Retired Items
A1: Retired or already-done items from the 23 Sep backlog
A3: ID | B3: Area | C3: Item | D3: Why retired / status
A4: I-01 | B4: AI layer | C4: VectorShift prompt not updated for the new input | D4: Retired — AI analysis removed (25 Sep 2026)
A5: I-02 | B5: AI layer | C5: Live AI can exceed Netlify's time limit (background function) | D5: Retired — AI analysis removed; background function deleted
A6: I-03 | B6: AI layer | C6: Semantic search (pgvector) not used | D6: Retired for now — no AI generation; revisit only if AI returns
A7: I-04 | B7: AI layer | C7: No admin view of AI usage and cost | D7: Retired — no paid AI calls remain
A8: U-04 | B8: User experience | C8: Stale AI write-up after saving an asking rent | D8: Retired — the Final Report is now computed live from module data
A9: R-01 to R-08 | B9: Regional expansion | C9: Region registry, boundaries, tiled Overpass, demographics, zonal, lease corridors, malls/traffic, regional QA | D9: Done in code (24 Sep 2026). Data loads carried forward as F-19
A10: — | B10: Stability | C10: Analysis-report 502 'Transactions are not supported in HTTP mode' | D10: Resolved by removing the AI report; the same query pattern is still in the pipeline → F-01 / F-02
A11: — | B11: UX | C11: React hydration errors #418 / #423 | D11: Resolved — deterministic number and Manila-time formatting
